enc_ds/__init__.py
enc_ds/datatree.py
enc_ds/enc_ds.py
enc_ds/enciphered_datastorage.py
enc_ds/share/data/cipher_diagram_0.mmd
enc_ds/share/data/cipher_diagram_0.png
enc_ds/share/data/cipher_diagram_1.mmd
enc_ds/share/data/cipher_diagram_1.png
enc_ds-0.0.3.dist-info/licenses/LICENSE
enc_ds-0.0.3.dist-info/METADATA
enc_ds-0.0.3.dist-info/WHEEL
enc_ds-0.0.3.dist-info/entry_points.txt
enc_ds-0.0.3.dist-info/top_level.txt
enc_ds-0.0.3.dist-info/RECORD
