Metadata-Version: 2.4
Name: enc-ds
Version: 0.0.3
Summary: Utility for simple encrypted data storage using RSA signatures via ssh-agent
Author-email: Nanigashi Uji <53845049+nanigashi-uji@users.noreply.github.com>, Nanigashi Uji <4423013-nanigashi_uji@users.noreply.gitlab.com>
License: BSD 3-Clause License
Project-URL: Homepage, https://github.com/nanigashi-uji/enc-ds
Keywords: ssh-agent,encryption
Requires-Python: >=3.8
License-File: LICENSE
Requires-Dist: cryptography
Requires-Dist: paramiko
Requires-Dist: PyNaCl
Requires-Dist: PyYAML
Requires-Dist: toml
Requires-Dist: pkgstruct
Requires-Dist: sshkeyring
Requires-Dist: argparse_extd
Dynamic: license-file
